<?xml version="1.0"?>
<PropertyList>
  <runway>
    <threshold>
      <lon>-76.139873219814</lon>
      <lat>38.5867276781511</lat>
      <rwy>03</rwy>
      <hdg-deg>20.00</hdg-deg>
      <displ-m>0</displ-m>
      <stopw-m>0</stopw-m>
    </threshold>
    <threshold>
      <lon>-76.1372326755621</lon>
      <lat>38.5923983070166</lat>
      <rwy>21</rwy>
      <hdg-deg>200.00</hdg-deg>
      <displ-m>0</displ-m>
      <stopw-m>0</stopw-m>
    </threshold>
  </runway>
  <runway>
    <threshold>
      <lon>-76.1431321275412</lon>
      <lat>38.5889317953048</lat>
      <rwy>09</rwy>
      <hdg-deg>80.00</hdg-deg>
      <displ-m>0</displ-m>
      <stopw-m>0</stopw-m>
    </threshold>
    <threshold>
      <lon>-76.1339737919119</lon>
      <lat>38.5901940262702</lat>
      <rwy>27</rwy>
      <hdg-deg>260.00</hdg-deg>
      <displ-m>0</displ-m>
      <stopw-m>0</stopw-m>
    </threshold>
  </runway>
  <runway>
    <threshold>
      <lon>-76.1409724981083</lon>
      <lat>38.5911498136106</lat>
      <rwy>14</rwy>
      <hdg-deg>130.00</hdg-deg>
      <displ-m>0</displ-m>
      <stopw-m>0</stopw-m>
    </threshold>
    <threshold>
      <lon>-76.1361336085448</lon>
      <lat>38.5879761365798</lat>
      <rwy>32</rwy>
      <hdg-deg>310.00</hdg-deg>
      <displ-m>0</displ-m>
      <stopw-m>0</stopw-m>
    </threshold>
  </runway>
</PropertyList>
