<?xml version="1.0"?>
<PropertyList>
  <runway>
    <threshold>
      <lon>-111.062654531374</lon>
      <lat>29.0880174166269</lat>
      <rwy>05</rwy>
      <hdg-deg>58.76</hdg-deg>
      <displ-m>0</displ-m>
      <stopw-m>56</stopw-m>
    </threshold>
    <threshold>
      <lon>-111.042372409884</lon>
      <lat>29.0987678207393</lat>
      <rwy>23</rwy>
      <hdg-deg>238.76</hdg-deg>
      <displ-m>0</displ-m>
      <stopw-m>58</stopw-m>
    </threshold>
  </runway>
  <runway>
    <threshold>
      <lon>-111.054356382689</lon>
      <lat>29.0999310782682</lat>
      <rwy>11</rwy>
      <hdg-deg>125.68</hdg-deg>
      <displ-m>0</displ-m>
      <stopw-m>0</stopw-m>
    </threshold>
    <threshold>
      <lon>-111.045181873861</lon>
      <lat>29.0941747656726</lat>
      <rwy>29</rwy>
      <hdg-deg>305.68</hdg-deg>
      <displ-m>0</displ-m>
      <stopw-m>0</stopw-m>
    </threshold>
  </runway>
</PropertyList>
