<?xml version="1.0"?>
<PropertyList>
  <runway>
    <threshold>
      <lon>14.8052187375197</lon>
      <lat>63.1276664519532</lat>
      <rwy>15</rwy>
      <hdg-deg>143.43</hdg-deg>
      <displ-m>0</displ-m>
      <stopw-m>0</stopw-m>
    </threshold>
    <threshold>
      <lon>14.8140364468923</lon>
      <lat>63.1222934112508</lat>
      <rwy>33</rwy>
      <hdg-deg>323.43</hdg-deg>
      <displ-m>0</displ-m>
      <stopw-m>0</stopw-m>
    </threshold>
  </runway>
  <runway>
    <threshold>
      <lon>14.8027762924527</lon>
      <lat>63.1330961446789</lat>
      <rwy>18</rwy>
      <hdg-deg>180.00</hdg-deg>
      <displ-m>0</displ-m>
      <stopw-m>0</stopw-m>
    </threshold>
    <threshold>
      <lon>14.802778</lon>
      <lat>63.1241238553212</lat>
      <rwy>36</rwy>
      <hdg-deg>0.00</hdg-deg>
      <displ-m>0</displ-m>
      <stopw-m>0</stopw-m>
    </threshold>
  </runway>
  <runway>
    <threshold>
      <lon>14.8065198361268</lon>
      <lat>63.1301877538672</lat>
      <rwy>18R</rwy>
      <hdg-deg>176.37</hdg-deg>
      <displ-m>0</displ-m>
      <stopw-m>0</stopw-m>
    </threshold>
    <threshold>
      <lon>14.8076240140179</lon>
      <lat>63.1223202439879</lat>
      <rwy>36L</rwy>
      <hdg-deg>356.37</hdg-deg>
      <displ-m>0</displ-m>
      <stopw-m>0</stopw-m>
    </threshold>
  </runway>
</PropertyList>
