<?xml version="1.0"?>
<PropertyList>
  <runway>
    <ils>
      <lon>8.59154700000001</lon>
      <lat>50.046217</lat>
      <rwy>07L</rwy>
      <hdg-deg>69.61</hdg-deg>
      <elev-m>110.95</elev-m>
      <nav-id>IFNE</nav-id>
    </ils>
    <ils>
      <lon>8.53079400000001</lon>
      <lat>50.0317</lat>
      <rwy>25R</rwy>
      <hdg-deg>249.57</hdg-deg>
      <elev-m>100.28</elev-m>
      <nav-id>IFNW</nav-id>
    </ils>
  </runway>
  <runway>
    <ils>
      <lon>8.59149200000001</lon>
      <lat>50.041236</lat>
      <rwy>07R</rwy>
      <hdg-deg>69.62</hdg-deg>
      <elev-m>110.34</elev-m>
      <nav-id>IFSE</nav-id>
    </ils>
    <ils>
      <lon>8.53075000000001</lon>
      <lat>50.026722</lat>
      <rwy>25L</rwy>
      <hdg-deg>249.57</hdg-deg>
      <elev-m>99.97</elev-m>
      <nav-id>IFSW</nav-id>
    </ils>
  </runway>
</PropertyList>
