<?xml version="1.0"?>
<PropertyList>
  <runway>
    <ils>
      <lon>-92.2157470000001</lon>
      <lat>34.739956</lat>
      <rwy>04L</rwy>
      <hdg-deg>46.39</hdg-deg>
      <elev-m>78.33</elev-m>
      <nav-id>ILIT</nav-id>
    </ils>
    <ils>
      <lon>-92.2397750000001</lon>
      <lat>34.721142</lat>
      <rwy>22R</rwy>
      <hdg-deg>226.38</hdg-deg>
      <elev-m>77.11</elev-m>
      <nav-id>IAAY</nav-id>
    </ils>
  </runway>
  <runway>
    <ils>
      <lon>-92.1988830000001</lon>
      <lat>34.736872</lat>
      <rwy>04R</rwy>
      <hdg-deg>46.40</hdg-deg>
      <elev-m>77.42</elev-m>
      <nav-id>ICNL</nav-id>
    </ils>
    <ils>
      <lon>-92.2208670000001</lon>
      <lat>34.719664</lat>
      <rwy>22L</rwy>
      <hdg-deg>226.39</hdg-deg>
      <elev-m>78.03</elev-m>
      <nav-id>IBWY</nav-id>
    </ils>
  </runway>
</PropertyList>
