<?xml version="1.0"?>
<PropertyList>
  <runway>
    <threshold>
      <lon>47.5080971911356</lon>
      <lat>29.3544919846711</lat>
      <rwy>12L</rwy>
      <hdg-deg>120.31</hdg-deg>
      <displ-m>0</displ-m>
      <stopw-m>101</stopw-m>
    </threshold>
    <threshold>
      <lon>47.5346990394975</lon>
      <lat>29.3409366962187</lat>
      <rwy>30R</rwy>
      <hdg-deg>300.31</hdg-deg>
      <displ-m>0</displ-m>
      <stopw-m>101</stopw-m>
    </threshold>
  </runway>
  <runway>
    <threshold>
      <lon>47.5068034457354</lon>
      <lat>29.3525419847237</lat>
      <rwy>12R</rwy>
      <hdg-deg>120.31</hdg-deg>
      <displ-m>0</displ-m>
      <stopw-m>296</stopw-m>
    </threshold>
    <threshold>
      <lon>47.533404785083</lon>
      <lat>29.3389866962713</lat>
      <rwy>30L</rwy>
      <hdg-deg>300.31</hdg-deg>
      <displ-m>0</displ-m>
      <stopw-m>296</stopw-m>
    </threshold>
  </runway>
</PropertyList>
