<?xml version="1.0"?>
<PropertyList>
  <runway>
    <threshold>
      <lon>-94.0952891251908</lon>
      <lat>43.5927541440991</lat>
      <rwy>03</rwy>
      <hdg-deg>34.31</hdg-deg>
      <displ-m>0</displ-m>
      <stopw-m>0</stopw-m>
    </threshold>
    <threshold>
      <lon>-94.0904066647506</lon>
      <lat>43.5979358039561</lat>
      <rwy>21</rwy>
      <hdg-deg>214.31</hdg-deg>
      <displ-m>0</displ-m>
      <stopw-m>0</stopw-m>
    </threshold>
  </runway>
  <runway>
    <threshold>
      <lon>-94.0945890978582</lon>
      <lat>43.5983246238206</lat>
      <rwy>16</rwy>
      <hdg-deg>161.16</hdg-deg>
      <displ-m>0</displ-m>
      <stopw-m>0</stopw-m>
    </threshold>
    <threshold>
      <lon>-94.0904332057535</lon>
      <lat>43.5895033385444</lat>
      <rwy>34</rwy>
      <hdg-deg>341.16</hdg-deg>
      <displ-m>0</displ-m>
      <stopw-m>0</stopw-m>
    </threshold>
  </runway>
</PropertyList>
