<?xml version="1.0"?>
<PropertyList>
  <runway>
    <threshold>
      <lon>-117.622810316897</lon>
      <lat>34.0568775386112</lat>
      <rwy>08L</rwy>
      <hdg-deg>89.98</hdg-deg>
      <displ-m>304</displ-m>
      <stopw-m>122</stopw-m>
    </threshold>
    <threshold>
      <lon>-117.582553680351</lon>
      <lat>34.05688918062</lat>
      <rwy>26R</rwy>
      <hdg-deg>269.98</hdg-deg>
      <displ-m>0</displ-m>
      <stopw-m>130</stopw-m>
    </threshold>
  </runway>
  <runway>
    <threshold>
      <lon>-117.616224294537</lon>
      <lat>34.0549579836897</lat>
      <rwy>08R</rwy>
      <hdg-deg>89.98</hdg-deg>
      <displ-m>0</displ-m>
      <stopw-m>122</stopw-m>
    </threshold>
    <threshold>
      <lon>-117.582553703515</lon>
      <lat>34.0549677212694</lat>
      <rwy>26L</rwy>
      <hdg-deg>269.98</hdg-deg>
      <displ-m>0</displ-m>
      <stopw-m>130</stopw-m>
    </threshold>
  </runway>
</PropertyList>
