<?xml version="1.0"?>
<PropertyList>
  <runway>
    <threshold>
      <lon>148.969521982165</lon>
      <lat>-36.3047866036096</lat>
      <rwy>14</rwy>
      <hdg-deg>150.09</hdg-deg>
      <displ-m>0</displ-m>
      <stopw-m>0</stopw-m>
    </threshold>
    <threshold>
      <lon>148.972986125571</lon>
      <lat>-36.309639371406</lat>
      <rwy>32</rwy>
      <hdg-deg>330.09</hdg-deg>
      <displ-m>0</displ-m>
      <stopw-m>0</stopw-m>
    </threshold>
  </runway>
  <runway>
    <threshold>
      <lon>148.975194362633</lon>
      <lat>-36.2904504176561</lat>
      <rwy>18</rwy>
      <hdg-deg>192.65</hdg-deg>
      <displ-m>71</displ-m>
      <stopw-m>0</stopw-m>
    </threshold>
    <threshold>
      <lon>148.970003016744</lon>
      <lat>-36.3090915262387</lat>
      <rwy>36</rwy>
      <hdg-deg>12.65</hdg-deg>
      <displ-m>0</displ-m>
      <stopw-m>0</stopw-m>
    </threshold>
  </runway>
</PropertyList>
