<?xml version="1.0"?>
<PropertyList>
  <runway>
    <threshold>
      <lon>-82.4446390575049</lon>
      <lat>27.067118025029</lat>
      <rwy>04</rwy>
      <hdg-deg>45.06</hdg-deg>
      <displ-m>0</displ-m>
      <stopw-m>0</stopw-m>
    </threshold>
    <threshold>
      <lon>-82.4337364713441</lon>
      <lat>27.0768057647895</lat>
      <rwy>22</rwy>
      <hdg-deg>225.06</hdg-deg>
      <displ-m>90</displ-m>
      <stopw-m>0</stopw-m>
    </threshold>
  </runway>
  <runway>
    <threshold>
      <lon>-82.4433324225061</lon>
      <lat>27.0733326262579</lat>
      <rwy>09</rwy>
      <hdg-deg>87.74</hdg-deg>
      <displ-m>0</displ-m>
      <stopw-m>0</stopw-m>
    </threshold>
    <threshold>
      <lon>-82.4275015382179</lon>
      <lat>27.0738889305787</lat>
      <rwy>27</rwy>
      <hdg-deg>267.74</hdg-deg>
      <displ-m>0</displ-m>
      <stopw-m>0</stopw-m>
    </threshold>
  </runway>
  <runway>
    <threshold>
      <lon>-82.4468855166476</lon>
      <lat>27.0761580586655</lat>
      <rwy>13</rwy>
      <hdg-deg>135.37</hdg-deg>
      <displ-m>0</displ-m>
      <stopw-m>0</stopw-m>
    </threshold>
    <threshold>
      <lon>-82.4360649545048</lon>
      <lat>27.0663977343072</lat>
      <rwy>31</rwy>
      <hdg-deg>315.37</hdg-deg>
      <displ-m>0</displ-m>
      <stopw-m>0</stopw-m>
    </threshold>
  </runway>
</PropertyList>
