<?xml version="1.0"?>
<PropertyList>
  <runway>
    <threshold>
      <lon>136.499209373789</lon>
      <lat>-33.7102470296715</lat>
      <rwy>08</rwy>
      <hdg-deg>90.67</hdg-deg>
      <displ-m>0</displ-m>
      <stopw-m>0</stopw-m>
    </threshold>
    <threshold>
      <lon>136.513756638087</lon>
      <lat>-33.7103885440282</lat>
      <rwy>26</rwy>
      <hdg-deg>270.67</hdg-deg>
      <displ-m>0</displ-m>
      <stopw-m>0</stopw-m>
    </threshold>
  </runway>
  <runway>
    <threshold>
      <lon>136.504256247016</lon>
      <lat>-33.7076901325254</lat>
      <rwy>18</rwy>
      <hdg-deg>181.60</hdg-deg>
      <displ-m>0</displ-m>
      <stopw-m>0</stopw-m>
    </threshold>
    <threshold>
      <lon>136.503985742205</lon>
      <lat>-33.7157458673272</lat>
      <rwy>36</rwy>
      <hdg-deg>1.60</hdg-deg>
      <displ-m>0</displ-m>
      <stopw-m>0</stopw-m>
    </threshold>
  </runway>
</PropertyList>
