<?xml version="1.0"?>
<PropertyList>
  <runway>
    <threshold>
      <lon>-77.3449980835916</lon>
      <lat>44.0647257865584</lat>
      <rwy>06</rwy>
      <hdg-deg>47.99</hdg-deg>
      <displ-m>0</displ-m>
      <stopw-m>152</stopw-m>
    </threshold>
    <threshold>
      <lon>-77.3308348196637</lon>
      <lat>44.0738917760355</lat>
      <rwy>24</rwy>
      <hdg-deg>227.99</hdg-deg>
      <displ-m>0</displ-m>
      <stopw-m>152</stopw-m>
    </threshold>
  </runway>
  <runway>
    <threshold>
      <lon>-77.3436131572499</lon>
      <lat>44.0738921246164</lat>
      <rwy>10</rwy>
      <hdg-deg>88.10</hdg-deg>
      <displ-m>0</displ-m>
      <stopw-m>0</stopw-m>
    </threshold>
    <threshold>
      <lon>-77.3322228165762</lon>
      <lat>44.0741635924831</lat>
      <rwy>28</rwy>
      <hdg-deg>268.10</hdg-deg>
      <displ-m>0</displ-m>
      <stopw-m>0</stopw-m>
    </threshold>
  </runway>
  <runway>
    <threshold>
      <lon>-77.3433303493795</lon>
      <lat>44.0755524368857</lat>
      <rwy>15</rwy>
      <hdg-deg>143.19</hdg-deg>
      <displ-m>0</displ-m>
      <stopw-m>0</stopw-m>
    </threshold>
    <threshold>
      <lon>-77.3363900413263</lon>
      <lat>44.0688894580835</lat>
      <rwy>33</rwy>
      <hdg-deg>323.19</hdg-deg>
      <displ-m>0</displ-m>
      <stopw-m>0</stopw-m>
    </threshold>
  </runway>
</PropertyList>
