<?xml version="1.0"?>
<PropertyList>
  <runway>
    <threshold>
      <lon>-118.06330046733</lon>
      <lat>36.5920296035111</lat>
      <rwy>13</rwy>
      <hdg-deg>143.64</hdg-deg>
      <displ-m>190</displ-m>
      <stopw-m>0</stopw-m>
    </threshold>
    <threshold>
      <lon>-118.058441699196</lon>
      <lat>36.5867303471889</lat>
      <rwy>31</rwy>
      <hdg-deg>323.64</hdg-deg>
      <displ-m>0</displ-m>
      <stopw-m>0</stopw-m>
    </threshold>
  </runway>
  <runway>
    <threshold>
      <lon>-118.05194</lon>
      <lat>36.5938861641103</lat>
      <rwy>16</rwy>
      <hdg-deg>180.00</hdg-deg>
      <displ-m>0</displ-m>
      <stopw-m>0</stopw-m>
    </threshold>
    <threshold>
      <lon>-118.05194</lon>
      <lat>36.5827798358898</lat>
      <rwy>34</rwy>
      <hdg-deg>0.00</hdg-deg>
      <displ-m>0</displ-m>
      <stopw-m>0</stopw-m>
    </threshold>
  </runway>
</PropertyList>
