<?xml version="1.0"?>
<PropertyList>
  <runway>
    <threshold>
      <lon>9.42700198165587</lon>
      <lat>52.4450011348312</lat>
      <rwy>03</rwy>
      <hdg-deg>26.81</hdg-deg>
      <displ-m>0</displ-m>
      <stopw-m>0</stopw-m>
    </threshold>
    <threshold>
      <lon>9.43833377637472</lon>
      <lat>52.4586665944469</lat>
      <rwy>21</rwy>
      <hdg-deg>206.81</hdg-deg>
      <displ-m>0</displ-m>
      <stopw-m>0</stopw-m>
    </threshold>
  </runway>
  <runway>
    <threshold>
      <lon>9.41350139235777</lon>
      <lat>52.4561673207482</lat>
      <rwy>08</rwy>
      <hdg-deg>82.03</hdg-deg>
      <displ-m>0</displ-m>
      <stopw-m>0</stopw-m>
    </threshold>
    <threshold>
      <lon>9.44083333137277</lon>
      <lat>52.4584991043814</lat>
      <rwy>26</rwy>
      <hdg-deg>262.03</hdg-deg>
      <displ-m>0</displ-m>
      <stopw-m>0</stopw-m>
    </threshold>
  </runway>
  <runway>
    <threshold>
      <lon>9.4163352343976</lon>
      <lat>52.4548326241404</lat>
      <rwy>08R</rwy>
      <hdg-deg>81.16</hdg-deg>
      <displ-m>0</displ-m>
      <stopw-m>0</stopw-m>
    </threshold>
    <threshold>
      <lon>9.43216503525906</lon>
      <lat>52.4563328475824</lat>
      <rwy>26L</rwy>
      <hdg-deg>261.16</hdg-deg>
      <displ-m>0</displ-m>
      <stopw-m>0</stopw-m>
    </threshold>
  </runway>
</PropertyList>
