<?xml version="1.0"?>
<PropertyList>
  <runway>
    <threshold>
      <lon>133.839668644884</lon>
      <lat>-23.5116719472954</lat>
      <rwy>12</rwy>
      <hdg-deg>120.00</hdg-deg>
      <displ-m>0</displ-m>
      <stopw-m>0</stopw-m>
    </threshold>
    <threshold>
      <lon>133.856437920463</lon>
      <lat>-23.5205496037825</lat>
      <rwy>30</rwy>
      <hdg-deg>300.00</hdg-deg>
      <displ-m>0</displ-m>
      <stopw-m>0</stopw-m>
    </threshold>
  </runway>
  <runway>
    <threshold>
      <lon>133.85547976746</lon>
      <lat>-23.5168854153696</lat>
      <rwy>27</rwy>
      <hdg-deg>209.00</hdg-deg>
      <displ-m>0</displ-m>
      <stopw-m>0</stopw-m>
    </threshold>
    <threshold>
      <lon>133.851674141559</lon>
      <lat>-23.5231805615072</lat>
      <rwy>09</rwy>
      <hdg-deg>29.00</hdg-deg>
      <displ-m>0</displ-m>
      <stopw-m>0</stopw-m>
    </threshold>
  </runway>
</PropertyList>
