<?xml version="1.0"?>
<PropertyList>
  <runway>
    <threshold>
      <lon>-92.1641182712768</lon>
      <lat>38.5910281051829</lat>
      <rwy>09</rwy>
      <hdg-deg>91.10</hdg-deg>
      <displ-m>0</displ-m>
      <stopw-m>0</stopw-m>
    </threshold>
    <threshold>
      <lon>-92.1522237435537</lon>
      <lat>38.5908495938482</lat>
      <rwy>27</rwy>
      <hdg-deg>271.10</hdg-deg>
      <displ-m>0</displ-m>
      <stopw-m>0</stopw-m>
    </threshold>
  </runway>
  <runway>
    <threshold>
      <lon>-92.163843285682</lon>
      <lat>38.5957349351259</lat>
      <rwy>12</rwy>
      <hdg-deg>122.63</hdg-deg>
      <displ-m>0</displ-m>
      <stopw-m>0</stopw-m>
    </threshold>
    <threshold>
      <lon>-92.1461458058086</lon>
      <lat>38.5868783986024</lat>
      <rwy>30</rwy>
      <hdg-deg>302.63</hdg-deg>
      <displ-m>0</displ-m>
      <stopw-m>0</stopw-m>
    </threshold>
  </runway>
</PropertyList>
