<?xml version="1.0"?>
<PropertyList>
  <runway>
    <threshold>
      <lon>-3.23799828987588</lon>
      <lat>50.8562260675695</lat>
      <rwy>05</rwy>
      <hdg-deg>40.92</hdg-deg>
      <displ-m>0</displ-m>
      <stopw-m>0</stopw-m>
    </threshold>
    <threshold>
      <lon>-3.22900107794646</lon>
      <lat>50.8627777595067</lat>
      <rwy>23</rwy>
      <hdg-deg>220.92</hdg-deg>
      <displ-m>295</displ-m>
      <stopw-m>0</stopw-m>
    </threshold>
  </runway>
  <runway>
    <threshold>
      <lon>-3.2402769085646</lon>
      <lat>50.8643060409525</lat>
      <rwy>09</rwy>
      <hdg-deg>82.82</hdg-deg>
      <displ-m>0</displ-m>
      <stopw-m>0</stopw-m>
    </threshold>
    <threshold>
      <lon>-3.22805696396165</lon>
      <lat>50.8652776400695</lat>
      <rwy>27</rwy>
      <hdg-deg>262.82</hdg-deg>
      <displ-m>0</displ-m>
      <stopw-m>0</stopw-m>
    </threshold>
  </runway>
  <runway>
    <threshold>
      <lon>-3.23500058875413</lon>
      <lat>50.8644433217082</lat>
      <rwy>17</rwy>
      <hdg-deg>169.77</hdg-deg>
      <displ-m>0</displ-m>
      <stopw-m>0</stopw-m>
    </threshold>
    <threshold>
      <lon>-3.2333335153116</lon>
      <lat>50.8586126723552</lat>
      <rwy>35</rwy>
      <hdg-deg>349.77</hdg-deg>
      <displ-m>0</displ-m>
      <stopw-m>0</stopw-m>
    </threshold>
  </runway>
</PropertyList>
