<?xml version="1.0"?>
<PropertyList>
  <runway>
    <threshold>
      <lon>-106.132626323097</lon>
      <lat>32.8468022353743</lat>
      <rwy>04</rwy>
      <hdg-deg>47.67</hdg-deg>
      <displ-m>0</displ-m>
      <stopw-m>354</stopw-m>
    </threshold>
    <threshold>
      <lon>-106.107112869719</lon>
      <lat>32.8663244701874</lat>
      <rwy>22</rwy>
      <hdg-deg>227.67</hdg-deg>
      <displ-m>0</displ-m>
      <stopw-m>305</stopw-m>
    </threshold>
  </runway>
  <runway>
    <threshold>
      <lon>-106.124637638194</lon>
      <lat>32.8462251431995</lat>
      <rwy>07</rwy>
      <hdg-deg>79.42</hdg-deg>
      <displ-m>0</displ-m>
      <stopw-m>648</stopw-m>
    </threshold>
    <threshold>
      <lon>-106.083288850102</lon>
      <lat>32.8527134572624</lat>
      <rwy>25</rwy>
      <hdg-deg>259.42</hdg-deg>
      <displ-m>0</displ-m>
      <stopw-m>335</stopw-m>
    </threshold>
  </runway>
  <runway>
    <threshold>
      <lon>-106.107689449248</lon>
      <lat>32.8665961288423</lat>
      <rwy>16</rwy>
      <hdg-deg>167.88</hdg-deg>
      <displ-m>0</displ-m>
      <stopw-m>305</stopw-m>
    </threshold>
    <threshold>
      <lon>-106.09935808064</lon>
      <lat>32.8340037331407</lat>
      <rwy>34</rwy>
      <hdg-deg>347.88</hdg-deg>
      <displ-m>0</displ-m>
      <stopw-m>305</stopw-m>
    </threshold>
  </runway>
</PropertyList>
