<?xml version="1.0"?>
<PropertyList>
  <runway>
    <threshold>
      <lon>137.914762901589</lon>
      <lat>-20.9759859770784</lat>
      <rwy>15</rwy>
      <hdg-deg>149.00</hdg-deg>
      <displ-m>0</displ-m>
      <stopw-m>0</stopw-m>
    </threshold>
    <threshold>
      <lon>137.92077728651</lon>
      <lat>-20.9853319701555</lat>
      <rwy>33</rwy>
      <hdg-deg>329.00</hdg-deg>
      <displ-m>0</displ-m>
      <stopw-m>0</stopw-m>
    </threshold>
  </runway>
  <runway>
    <threshold>
      <lon>137.923077090954</lon>
      <lat>-20.9828622920767</lat>
      <rwy>29</rwy>
      <hdg-deg>293.00</hdg-deg>
      <displ-m>0</displ-m>
      <stopw-m>0</stopw-m>
    </threshold>
    <threshold>
      <lon>137.916156972458</lon>
      <lat>-20.9801196380658</lat>
      <rwy>11</rwy>
      <hdg-deg>113.00</hdg-deg>
      <displ-m>0</displ-m>
      <stopw-m>0</stopw-m>
    </threshold>
  </runway>
</PropertyList>
