<?xml version="1.0"?>
<PropertyList>
  <runway>
    <threshold>
      <lon>-2.26598469879012</lon>
      <lat>52.5162249226339</lat>
      <rwy>04</rwy>
      <hdg-deg>34.06</hdg-deg>
      <displ-m>30</displ-m>
      <stopw-m>0</stopw-m>
    </threshold>
    <threshold>
      <lon>-2.26068301330554</lon>
      <lat>52.5209970181441</lat>
      <rwy>22</rwy>
      <hdg-deg>214.06</hdg-deg>
      <displ-m>90</displ-m>
      <stopw-m>0</stopw-m>
    </threshold>
  </runway>
  <runway>
    <threshold>
      <lon>-2.26720129734079</lon>
      <lat>52.5172368751454</lat>
      <rwy>10</rwy>
      <hdg-deg>97.43</hdg-deg>
      <displ-m>158</displ-m>
      <stopw-m>0</stopw-m>
    </threshold>
    <threshold>
      <lon>-2.2558348194395</lon>
      <lat>52.5163348526381</lat>
      <rwy>28</rwy>
      <hdg-deg>277.43</hdg-deg>
      <displ-m>140</displ-m>
      <stopw-m>0</stopw-m>
    </threshold>
  </runway>
  <runway>
    <threshold>
      <lon>-2.26297482403529</lon>
      <lat>52.5220022986329</lat>
      <rwy>16</rwy>
      <hdg-deg>156.27</hdg-deg>
      <displ-m>219</displ-m>
      <stopw-m>0</stopw-m>
    </threshold>
    <threshold>
      <lon>-2.25646984236834</lon>
      <lat>52.5129976122108</lat>
      <rwy>34</rwy>
      <hdg-deg>336.27</hdg-deg>
      <displ-m>187</displ-m>
      <stopw-m>0</stopw-m>
    </threshold>
  </runway>
</PropertyList>
