<?xml version="1.0"?>
<PropertyList>
  <runway>
    <threshold>
      <lon>-102.196957411013</lon>
      <lat>33.1657809784316</lat>
      <rwy>02</rwy>
      <hdg-deg>25.87</hdg-deg>
      <displ-m>0</displ-m>
      <stopw-m>0</stopw-m>
    </threshold>
    <threshold>
      <lon>-102.18949204034</lon>
      <lat>33.1786669101972</lat>
      <rwy>20</rwy>
      <hdg-deg>205.87</hdg-deg>
      <displ-m>0</displ-m>
      <stopw-m>0</stopw-m>
    </threshold>
  </runway>
  <runway>
    <threshold>
      <lon>-102.195549155361</lon>
      <lat>33.1775574541022</lat>
      <rwy>13</rwy>
      <hdg-deg>135.02</hdg-deg>
      <displ-m>0</displ-m>
      <stopw-m>0</stopw-m>
    </threshold>
    <threshold>
      <lon>-102.189151040141</lon>
      <lat>33.1721984640905</lat>
      <rwy>31</rwy>
      <hdg-deg>315.02</hdg-deg>
      <displ-m>0</displ-m>
      <stopw-m>0</stopw-m>
    </threshold>
  </runway>
</PropertyList>
