<?xml version="1.0"?>
<PropertyList>
  <runway>
    <threshold>
      <lon>59.255072671826</lon>
      <lat>32.8950459326408</lat>
      <rwy>08</rwy>
      <hdg-deg>78.64</hdg-deg>
      <displ-m>0</displ-m>
      <stopw-m>0</stopw-m>
    </threshold>
    <threshold>
      <lon>59.2777358172867</lon>
      <lat>32.8988690453401</lat>
      <rwy>26</rwy>
      <hdg-deg>258.64</hdg-deg>
      <displ-m>0</displ-m>
      <stopw-m>0</stopw-m>
    </threshold>
  </runway>
  <runway>
    <threshold>
      <lon>59.2696641824468</lon>
      <lat>32.8965045540519</lat>
      <rwy>10</rwy>
      <hdg-deg>98.77</hdg-deg>
      <displ-m>250</displ-m>
      <stopw-m>120</stopw-m>
    </threshold>
    <threshold>
      <lon>59.3003191304729</lon>
      <lat>32.8925335761134</lat>
      <rwy>28</rwy>
      <hdg-deg>278.77</hdg-deg>
      <displ-m>0</displ-m>
      <stopw-m>120</stopw-m>
    </threshold>
  </runway>
</PropertyList>
