<?xml version="1.0"?>
<PropertyList>
  <runway>
    <threshold>
      <lon>-85.2126902607967</lon>
      <lat>40.9626859105258</lat>
      <rwy>05</rwy>
      <hdg-deg>44.16</hdg-deg>
      <displ-m>0</displ-m>
      <stopw-m>61</stopw-m>
    </threshold>
    <threshold>
      <lon>-85.1823583178586</lon>
      <lat>40.9862681020707</lat>
      <rwy>23</rwy>
      <hdg-deg>224.16</hdg-deg>
      <displ-m>0</displ-m>
      <stopw-m>286</stopw-m>
    </threshold>
  </runway>
  <runway>
    <threshold>
      <lon>-85.1987816875006</lon>
      <lat>40.9758684083194</lat>
      <rwy>09</rwy>
      <hdg-deg>90.08</hdg-deg>
      <displ-m>0</displ-m>
      <stopw-m>0</stopw-m>
    </threshold>
    <threshold>
      <lon>-85.1842963141099</lon>
      <lat>40.9758531384201</lat>
      <rwy>27</rwy>
      <hdg-deg>270.08</hdg-deg>
      <displ-m>0</displ-m>
      <stopw-m>0</stopw-m>
    </threshold>
  </runway>
  <runway>
    <threshold>
      <lon>-85.2036612828572</lon>
      <lat>40.9935195642893</lat>
      <rwy>14</rwy>
      <hdg-deg>134.87</hdg-deg>
      <displ-m>0</displ-m>
      <stopw-m>46</stopw-m>
    </threshold>
    <threshold>
      <lon>-85.1830851294365</lon>
      <lat>40.9780575210961</lat>
      <rwy>32</rwy>
      <hdg-deg>314.87</hdg-deg>
      <displ-m>0</displ-m>
      <stopw-m>122</stopw-m>
    </threshold>
  </runway>
</PropertyList>
