<?xml version="1.0"?>
<PropertyList>
  <runway>
    <threshold>
      <lon>-161.824938935876</lon>
      <lat>59.0118973706467</lat>
      <rwy>09</rwy>
      <hdg-deg>108.20</hdg-deg>
      <displ-m>0</displ-m>
      <stopw-m>0</stopw-m>
    </threshold>
    <threshold>
      <lon>-161.815257294737</lon>
      <lat>59.0102584488311</lat>
      <rwy>27</rwy>
      <hdg-deg>288.20</hdg-deg>
      <displ-m>0</displ-m>
      <stopw-m>0</stopw-m>
    </threshold>
  </runway>
  <runway>
    <threshold>
      <lon>-161.823138836298</lon>
      <lat>59.0156074483688</lat>
      <rwy>13</rwy>
      <hdg-deg>154.89</hdg-deg>
      <displ-m>0</displ-m>
      <stopw-m>0</stopw-m>
    </threshold>
    <threshold>
      <lon>-161.815694048332</lon>
      <lat>59.0074284448896</lat>
      <rwy>31</rwy>
      <hdg-deg>334.89</hdg-deg>
      <displ-m>0</displ-m>
      <stopw-m>0</stopw-m>
    </threshold>
  </runway>
</PropertyList>
