<?xml version="1.0"?>
<PropertyList>
  <runway>
    <threshold>
      <lon>-56.0409533193531</lon>
      <lat>-28.6585168186804</lat>
      <rwy>06</rwy>
      <hdg-deg>56.09</hdg-deg>
      <displ-m>0</displ-m>
      <stopw-m>0</stopw-m>
    </threshold>
    <threshold>
      <lon>-56.0281511416733</lon>
      <lat>-28.6509648803928</lat>
      <rwy>24</rwy>
      <hdg-deg>236.09</hdg-deg>
      <displ-m>0</displ-m>
      <stopw-m>0</stopw-m>
    </threshold>
  </runway>
  <runway>
    <threshold>
      <lon>-56.0384467554468</lon>
      <lat>-28.6462677468774</lat>
      <rwy>13</rwy>
      <hdg-deg>122.48</hdg-deg>
      <displ-m>0</displ-m>
      <stopw-m>0</stopw-m>
    </threshold>
    <threshold>
      <lon>-56.0297930452576</lon>
      <lat>-28.6511021156428</lat>
      <rwy>31</rwy>
      <hdg-deg>302.48</hdg-deg>
      <displ-m>0</displ-m>
      <stopw-m>0</stopw-m>
    </threshold>
  </runway>
</PropertyList>
