<?xml version="1.0"?>
<PropertyList>
  <runway>
    <threshold>
      <lon>65.2810064522734</lon>
      <lat>57.169210380852</lat>
      <rwy>03</rwy>
      <hdg-deg>47.76</hdg-deg>
      <displ-m>0</displ-m>
      <stopw-m>49</stopw-m>
    </threshold>
    <threshold>
      <lon>65.3177225244844</lon>
      <lat>57.1872809398763</lat>
      <rwy>21</rwy>
      <hdg-deg>227.76</hdg-deg>
      <displ-m>0</displ-m>
      <stopw-m>44</stopw-m>
    </threshold>
  </runway>
  <runway>
    <threshold>
      <lon>65.3239363484662</lon>
      <lat>57.1897658354551</lat>
      <rwy>12</rwy>
      <hdg-deg>134.83</hdg-deg>
      <displ-m>0</displ-m>
      <stopw-m>50</stopw-m>
    </threshold>
    <threshold>
      <lon>65.3555183799495</lon>
      <lat>57.1727501822704</lat>
      <rwy>30</rwy>
      <hdg-deg>314.83</hdg-deg>
      <displ-m>0</displ-m>
      <stopw-m>27</stopw-m>
    </threshold>
  </runway>
</PropertyList>
