<?xml version="1.0"?>
<PropertyList>
  <runway>
    <threshold>
      <lon>-119.778838503635</lon>
      <lat>39.4962858956707</lat>
      <rwy>07</rwy>
      <hdg-deg>90.25</hdg-deg>
      <displ-m>0</displ-m>
      <stopw-m>0</stopw-m>
    </threshold>
    <threshold>
      <lon>-119.757219507661</lon>
      <lat>39.4962131034219</lat>
      <rwy>25</rwy>
      <hdg-deg>270.25</hdg-deg>
      <displ-m>0</displ-m>
      <stopw-m>0</stopw-m>
    </threshold>
  </runway>
  <runway>
    <threshold>
      <lon>-119.766740252293</lon>
      <lat>39.5138382471321</lat>
      <rwy>16L</rwy>
      <hdg-deg>180.11</hdg-deg>
      <displ-m>0</displ-m>
      <stopw-m>43</stopw-m>
    </threshold>
    <threshold>
      <lon>-119.766801735851</lon>
      <lat>39.4891377528598</lat>
      <rwy>34R</rwy>
      <hdg-deg>0.11</hdg-deg>
      <displ-m>0</displ-m>
      <stopw-m>0</stopw-m>
    </threshold>
  </runway>
  <runway>
    <threshold>
      <lon>-119.769219009973</lon>
      <lat>39.5138433317918</lat>
      <rwy>16R</rwy>
      <hdg-deg>180.12</hdg-deg>
      <displ-m>304</displ-m>
      <stopw-m>61</stopw-m>
    </threshold>
    <threshold>
      <lon>-119.769300981135</lon>
      <lat>39.4836486681939</lat>
      <rwy>34L</rwy>
      <hdg-deg>0.12</hdg-deg>
      <displ-m>302</displ-m>
      <stopw-m>0</stopw-m>
    </threshold>
  </runway>
</PropertyList>
