<?xml version="1.0"?>
<PropertyList>
  <runway>
    <threshold>
      <lon>-124.260626832722</lon>
      <lat>43.4147214124471</lat>
      <rwy>04</rwy>
      <hdg-deg>60.58</hdg-deg>
      <displ-m>0</displ-m>
      <stopw-m>0</stopw-m>
    </threshold>
    <threshold>
      <lon>-124.243170136562</lon>
      <lat>43.4218719237348</lat>
      <rwy>22</rwy>
      <hdg-deg>240.58</hdg-deg>
      <displ-m>0</displ-m>
      <stopw-m>305</stopw-m>
    </threshold>
  </runway>
  <runway>
    <threshold>
      <lon>-124.246268006813</lon>
      <lat>43.4198355469467</lat>
      <rwy>13</rwy>
      <hdg-deg>149.72</hdg-deg>
      <displ-m>0</displ-m>
      <stopw-m>0</stopw-m>
    </threshold>
    <threshold>
      <lon>-124.23776273632</lon>
      <lat>43.4092542954744</lat>
      <rwy>31</rwy>
      <hdg-deg>329.72</hdg-deg>
      <displ-m>0</displ-m>
      <stopw-m>0</stopw-m>
    </threshold>
  </runway>
  <runway>
    <threshold>
      <lon>-124.240308313695</lon>
      <lat>43.4224779845064</lat>
      <rwy>16</rwy>
      <hdg-deg>179.29</hdg-deg>
      <displ-m>0</displ-m>
      <stopw-m>107</stopw-m>
    </threshold>
    <threshold>
      <lon>-124.240199699728</lon>
      <lat>43.416112015468</lat>
      <rwy>34</rwy>
      <hdg-deg>359.29</hdg-deg>
      <displ-m>0</displ-m>
      <stopw-m>0</stopw-m>
    </threshold>
  </runway>
</PropertyList>
