<?xml version="1.0"?>
<PropertyList>
  <runway>
    <threshold>
      <lon>-135.718191335795</lon>
      <lat>58.4200637824485</lat>
      <rwy>02</rwy>
      <hdg-deg>40.96</hdg-deg>
      <displ-m>0</displ-m>
      <stopw-m>0</stopw-m>
    </threshold>
    <threshold>
      <lon>-135.707889754882</lon>
      <lat>58.4262780109814</lat>
      <rwy>20</rwy>
      <hdg-deg>220.96</hdg-deg>
      <displ-m>0</displ-m>
      <stopw-m>0</stopw-m>
    </threshold>
  </runway>
  <runway>
    <threshold>
      <lon>-135.717280968348</lon>
      <lat>58.4327129871996</lat>
      <rwy>11</rwy>
      <hdg-deg>135.07</hdg-deg>
      <displ-m>0</displ-m>
      <stopw-m>0</stopw-m>
    </threshold>
    <threshold>
      <lon>-135.692499608684</lon>
      <lat>58.4197058174736</lat>
      <rwy>29</rwy>
      <hdg-deg>315.07</hdg-deg>
      <displ-m>0</displ-m>
      <stopw-m>0</stopw-m>
    </threshold>
  </runway>
</PropertyList>
