<?xml version="1.0"?>
<PropertyList>
  <runway>
    <threshold>
      <lon>-82.4528527334964</lon>
      <lat>28.4641283024765</lat>
      <rwy>03</rwy>
      <hdg-deg>25.95</hdg-deg>
      <displ-m>0</displ-m>
      <stopw-m>0</stopw-m>
    </threshold>
    <threshold>
      <lon>-82.4459928642036</lon>
      <lat>28.4765196114801</lat>
      <rwy>21</rwy>
      <hdg-deg>205.95</hdg-deg>
      <displ-m>0</displ-m>
      <stopw-m>0</stopw-m>
    </threshold>
  </runway>
  <runway>
    <threshold>
      <lon>-82.4706131827794</lon>
      <lat>28.4759081354736</lat>
      <rwy>09</rwy>
      <hdg-deg>89.80</hdg-deg>
      <displ-m>0</displ-m>
      <stopw-m>0</stopw-m>
    </threshold>
    <threshold>
      <lon>-82.4488228102962</lon>
      <lat>28.475974996224</lat>
      <rwy>27</rwy>
      <hdg-deg>269.80</hdg-deg>
      <displ-m>0</displ-m>
      <stopw-m>0</stopw-m>
    </threshold>
  </runway>
</PropertyList>
