<?xml version="1.0"?>
<PropertyList>
  <runway>
    <threshold>
      <lon>28.8998077266849</lon>
      <lat>61.2446346640831</lat>
      <rwy>01</rwy>
      <hdg-deg>22.44</hdg-deg>
      <displ-m>0</displ-m>
      <stopw-m>0</stopw-m>
    </threshold>
    <threshold>
      <lon>28.9075853939351</lon>
      <lat>61.2536932246098</lat>
      <rwy>19</rwy>
      <hdg-deg>202.44</hdg-deg>
      <displ-m>0</displ-m>
      <stopw-m>0</stopw-m>
    </threshold>
  </runway>
  <runway>
    <threshold>
      <lon>28.8896936435234</lon>
      <lat>61.2498578012459</lat>
      <rwy>09</rwy>
      <hdg-deg>96.48</hdg-deg>
      <displ-m>0</displ-m>
      <stopw-m>0</stopw-m>
    </threshold>
    <threshold>
      <lon>28.9174976846482</lon>
      <lat>61.2483387762908</lat>
      <rwy>27</rwy>
      <hdg-deg>276.48</hdg-deg>
      <displ-m>0</displ-m>
      <stopw-m>0</stopw-m>
    </threshold>
  </runway>
</PropertyList>
