<?xml version="1.0"?>
<PropertyList>
  <runway>
    <ils>
      <lon>-122.311231</lon>
      <lat>47.435778</lat>
      <rwy>16C</rwy>
      <hdg-deg>180.34</hdg-deg>
      <elev-m>108.20</elev-m>
      <nav-id>ISZI</nav-id>
    </ils>
    <ils>
      <lon>-122.310975</lon>
      <lat>47.465097</lat>
      <rwy>34C</rwy>
      <hdg-deg>0.33</hdg-deg>
      <elev-m>128.63</elev-m>
      <nav-id>ITUC</nav-id>
    </ils>
  </runway>
  <runway>
    <ils>
      <lon>-122.308056</lon>
      <lat>47.429392</lat>
      <rwy>16L</rwy>
      <hdg-deg>180.35</hdg-deg>
      <elev-m>103.02</elev-m>
      <nav-id>ISNQ</nav-id>
    </ils>
    <ils>
      <lon>-122.307739</lon>
      <lat>47.465075</lat>
      <rwy>34R</rwy>
      <hdg-deg>0.34</hdg-deg>
      <elev-m>130.45</elev-m>
      <nav-id>ISEA</nav-id>
    </ils>
  </runway>
</PropertyList>
